README.rst
setup.py
py_aws_helper/__init__.py
py_aws_helper/s3objectfinder.py
py_aws_helper.egg-info/PKG-INFO
py_aws_helper.egg-info/SOURCES.txt
py_aws_helper.egg-info/dependency_links.txt
py_aws_helper.egg-info/requires.txt
py_aws_helper.egg-info/top_level.txt