Metadata-Version: 1.0
Name: py-aws-helper
Version: 0.0.4
Summary: Helper for AWS services like S3 written in python...
Home-page: https://github.com/1CloudHub/py_aws_helper.git
Author: Sripranav P
Author-email: sripranav@1cloudhub.com
License: MIT
Platform: UNKNOWN
